{"text": "Frequent expression of new cancer/testis gene D40/AF15q14 in lung cancers of smokers\nWe found a significant correlation between lung cancer in smokers and the expression of a human gene, D40, predominantly expressed in testis and cancers. In an attempt to clone a novel human gene, we screened a cDNA library derived from a human B cell line and obtained a cDNA clone that we refer to as D40. A search for public databases for sequence homologies showed that the D40 gene is identical to AF15q14. D40 mRNA is predominantly expressed in normal testis tissue. However, this gene is also expressed in various human tumour cell lines and primary tumours derived from various organs and tissues, such as lung cancer. We examined the relationship between D40 expression and clinico-pathological characteristics of tumours in primary lung cancer. D40 expression did not significantly correlate with either histological type or pathological tumour stage. However, D40 expression was observed more frequently in poorly differentiated tumours than in well or moderately differentiated ones. Furthermore, the incidence of D40 expression was significantly higher in tumours from patients who smoke than in those from non-smokers. D40/AF15q14 is the first gene in the cancer/testis family for which expression is related to the smoking habits of cancer patients.\nBritish Journal of Cancer (2002) 86, 1757\u20131762. doi:10.1038/sj.bjc.6600328 www.bjcancer.com\n\u00a9 2002 Cancer Research UK", "sourcedb": "PMC", "sourceid": "2375411", "divid": 0, "denotations": [{"span": {"begin": 0, "end": 8}, "obj": "http://ncicb.nci.nih.gov/xml/owl/EVS/Thesaurus.owl#C64649"}, {"span": {"begin": 989, "end": 999}, "obj": "http://ncicb.nci.nih.gov/xml/owl/EVS/Thesaurus.owl#C64649"}, {"span": {"begin": 0, "end": 8}, "obj": "http://purl.bioontology.org/ontology/SNOMEDCT/70232002"}, {"span": {"begin": 9, "end": 19}, "obj": "http://ncicb.nci.nih.gov/xml/owl/EVS/Thesaurus.owl#C80488"}, {"span": {"begin": 159, "end": 169}, "obj": "http://ncicb.nci.nih.gov/xml/owl/EVS/Thesaurus.owl#C80488"}, {"span": {"begin": 753, "end": 763}, "obj": "http://ncicb.nci.nih.gov/xml/owl/EVS/Thesaurus.owl#C80488"}, {"span": {"begin": 844, "end": 854}, "obj": "http://ncicb.nci.nih.gov/xml/owl/EVS/Thesaurus.owl#C80488"}, {"span": {"begin": 960, "end": 970}, "obj": "http://ncicb.nci.nih.gov/xml/owl/EVS/Thesaurus.owl#C80488"}, {"span": {"begin": 1115, "end": 1125}, "obj": "http://ncicb.nci.nih.gov/xml/owl/EVS/Thesaurus.owl#C80488"}, {"span": {"begin": 1286, "end": 1296}, "obj": "http://ncicb.nci.nih.gov/xml/owl/EVS/Thesaurus.owl#C80488"}, {"span": {"begin": 9, "end": 19}, "obj": "http://purl.bioontology.org/ontology/SNOMEDCT/706999006"}, {"span": {"begin": 159, "end": 169}, "obj": "http://purl.bioontology.org/ontology/SNOMEDCT/706999006"}, {"span": {"begin": 753, "end": 763}, "obj": "http://purl.bioontology.org/ontology/SNOMEDCT/706999006"}, {"span": {"begin": 844, "end": 854}, "obj": "http://purl.bioontology.org/ontology/SNOMEDCT/706999006"}, {"span": {"begin": 960, "end": 970}, "obj": "http://purl.bioontology.org/ontology/SNOMEDCT/706999006"}, {"span": {"begin": 1115, "end": 1125}, "obj": "http://purl.bioontology.org/ontology/SNOMEDCT/706999006"}, {"span": {"begin": 1286, "end": 1296}, "obj": "http://purl.bioontology.org/ontology/SNOMEDCT/706999006"}, {"span": {"begin": 9, "end": 19}, "obj": "http://ncicb.nci.nih.gov/xml/owl/EVS/Thesaurus.owl#C16608"}, {"span": {"begin": 159, "end": 169}, "obj": "http://ncicb.nci.nih.gov/xml/owl/EVS/Thesaurus.owl#C16608"}, {"span": {"begin": 206, "end": 215}, "obj": "http://ncicb.nci.nih.gov/xml/owl/EVS/Thesaurus.owl#C16608"}, {"span": {"begin": 523, "end": 532}, "obj": "http://ncicb.nci.nih.gov/xml/owl/EVS/Thesaurus.owl#C16608"}, {"span": {"begin": 585, "end": 594}, "obj": "http://ncicb.nci.nih.gov/xml/owl/EVS/Thesaurus.owl#C16608"}, {"span": {"begin": 753, "end": 763}, "obj": "http://ncicb.nci.nih.gov/xml/owl/EVS/Thesaurus.owl#C16608"}, {"span": {"begin": 844, "end": 854}, "obj": "http://ncicb.nci.nih.gov/xml/owl/EVS/Thesaurus.owl#C16608"}, {"span": {"begin": 960, "end": 970}, "obj": "http://ncicb.nci.nih.gov/xml/owl/EVS/Thesaurus.owl#C16608"}, {"span": {"begin": 1115, "end": 1125}, "obj": "http://ncicb.nci.nih.gov/xml/owl/EVS/Thesaurus.owl#C16608"}, {"span": {"begin": 1286, "end": 1296}, "obj": "http://ncicb.nci.nih.gov/xml/owl/EVS/Thesaurus.owl#C16608"}, {"span": {"begin": 9, "end": 19}, "obj": "http://purl.bioontology.org/ontology/SNOMEDCT/10012005"}, {"span": {"begin": 159, "end": 169}, "obj": "http://purl.bioontology.org/ontology/SNOMEDCT/10012005"}, {"span": {"begin": 753, "end": 763}, "obj": "http://purl.bioontology.org/ontology/SNOMEDCT/10012005"}, {"span": {"begin": 844, "end": 854}, "obj": "http://purl.bioontology.org/ontology/SNOMEDCT/10012005"}, {"span": {"begin": 960, "end": 970}, "obj": "http://purl.bioontology.org/ontology/SNOMEDCT/10012005"}, {"span": {"begin": 1115, "end": 1125}, "obj": "http://purl.bioontology.org/ontology/SNOMEDCT/10012005"}, {"span": {"begin": 1286, "end": 1296}, "obj": "http://purl.bioontology.org/ontology/SNOMEDCT/10012005"}, {"span": {"begin": 27, "end": 33}, "obj": "http://ncicb.nci.nih.gov/xml/owl/EVS/Thesaurus.owl#C9305"}, {"span": {"begin": 133, "end": 139}, "obj": "http://ncicb.nci.nih.gov/xml/owl/EVS/Thesaurus.owl#C9305"}, {"span": {"begin": 704, "end": 710}, "obj": "http://ncicb.nci.nih.gov/xml/owl/EVS/Thesaurus.owl#C9305"}, {"span": {"begin": 832, "end": 838}, "obj": "http://ncicb.nci.nih.gov/xml/owl/EVS/Thesaurus.owl#C9305"}, {"span": {"begin": 1255, "end": 1261}, "obj": "http://ncicb.nci.nih.gov/xml/owl/EVS/Thesaurus.owl#C9305"}, {"span": {"begin": 1333, "end": 1339}, "obj": "http://ncicb.nci.nih.gov/xml/owl/EVS/Thesaurus.owl#C9305"}, {"span": {"begin": 1369, "end": 1375}, "obj": "http://ncicb.nci.nih.gov/xml/owl/EVS/Thesaurus.owl#C9305"}, {"span": {"begin": 1449, "end": 1455}, "obj": "http://ncicb.nci.nih.gov/xml/owl/EVS/Thesaurus.owl#C9305"}, {"span": {"begin": 27, "end": 33}, "obj": "http://purl.bioontology.org/ontology/MEDLINEPLUS/C0006826"}, {"span": {"begin": 133, "end": 139}, "obj": "http://purl.bioontology.org/ontology/MEDLINEPLUS/C0006826"}, {"span": {"begin": 704, "end": 710}, "obj": "http://purl.bioontology.org/ontology/MEDLINEPLUS/C0006826"}, {"span": {"begin": 832, "end": 838}, "obj": "http://purl.bioontology.org/ontology/MEDLINEPLUS/C0006826"}, {"span": {"begin": 1255, "end": 1261}, "obj": "http://purl.bioontology.org/ontology/MEDLINEPLUS/C0006826"}, {"span": {"begin": 1333, "end": 1339}, "obj": "http://purl.bioontology.org/ontology/MEDLINEPLUS/C0006826"}, {"span": {"begin": 1369, "end": 1375}, "obj": "http://purl.bioontology.org/ontology/MEDLINEPLUS/C0006826"}, {"span": {"begin": 1449, "end": 1455}, "obj": "http://purl.bioontology.org/ontology/MEDLINEPLUS/C0006826"}, {"span": {"begin": 27, "end": 33}, "obj": "http://purl.bioontology.org/ontology/MEDDRA/10007050"}, {"span": {"begin": 133, "end": 139}, "obj": "http://purl.bioontology.org/ontology/MEDDRA/10007050"}, {"span": {"begin": 704, "end": 710}, "obj": "http://purl.bioontology.org/ontology/MEDDRA/10007050"}, {"span": {"begin": 832, "end": 838}, "obj": "http://purl.bioontology.org/ontology/MEDDRA/10007050"}, {"span": {"begin": 1255, "end": 1261}, "obj": "http://purl.bioontology.org/ontology/MEDDRA/10007050"}, {"span": {"begin": 1333, "end": 1339}, "obj": "http://purl.bioontology.org/ontology/MEDDRA/10007050"}, {"span": {"begin": 1369, "end": 1375}, "obj": "http://purl.bioontology.org/ontology/MEDDRA/10007050"}, {"span": {"begin": 1449, "end": 1455}, "obj": "http://purl.bioontology.org/ontology/MEDDRA/10007050"}, {"span": {"begin": 27, "end": 33}, "obj": "http://purl.obolibrary.org/obo/OBI_1110053"}, {"span": {"begin": 133, "end": 139}, "obj": "http://purl.obolibrary.org/obo/OBI_1110053"}, {"span": {"begin": 704, "end": 710}, "obj": "http://purl.obolibrary.org/obo/OBI_1110053"}, {"span": {"begin": 832, "end": 838}, "obj": "http://purl.obolibrary.org/obo/OBI_1110053"}, {"span": {"begin": 1255, "end": 1261}, "obj": "http://purl.obolibrary.org/obo/OBI_1110053"}, {"span": {"begin": 1333, "end": 1339}, "obj": "http://purl.obolibrary.org/obo/OBI_1110053"}, {"span": {"begin": 1369, "end": 1375}, "obj": "http://purl.obolibrary.org/obo/OBI_1110053"}, {"span": {"begin": 1449, "end": 1455}, "obj": "http://purl.obolibrary.org/obo/OBI_1110053"}, {"span": {"begin": 34, "end": 40}, "obj": "http://purl.org/sig/ont/fma/fma7210"}, {"span": {"begin": 219, "end": 225}, "obj": "http://purl.org/sig/ont/fma/fma7210"}, {"span": {"begin": 543, "end": 549}, "obj": "http://purl.org/sig/ont/fma/fma7210"}, {"span": {"begin": 1262, "end": 1268}, "obj": "http://purl.org/sig/ont/fma/fma7210"}, {"span": {"begin": 34, "end": 40}, "obj": "http://purl.bioontology.org/ontology/MESH/D013737"}, {"span": {"begin": 219, "end": 225}, "obj": "http://purl.bioontology.org/ontology/MESH/D013737"}, {"span": {"begin": 543, "end": 549}, "obj": "http://purl.bioontology.org/ontology/MESH/D013737"}, {"span": {"begin": 1262, "end": 1268}, "obj": "http://purl.bioontology.org/ontology/MESH/D013737"}, {"span": {"begin": 34, "end": 40}, "obj": "http://purl.obolibrary.org/obo/UBERON_0000473"}, {"span": {"begin": 219, "end": 225}, "obj": "http://purl.obolibrary.org/obo/UBERON_0000473"}, {"span": {"begin": 543, "end": 549}, "obj": "http://purl.obolibrary.org/obo/UBERON_0000473"}, {"span": {"begin": 1262, "end": 1268}, "obj": "http://purl.obolibrary.org/obo/UBERON_0000473"}, {"span": {"begin": 34, "end": 40}, "obj": "http://ncicb.nci.nih.gov/xml/owl/EVS/Thesaurus.owl#C12412"}, {"span": {"begin": 219, "end": 225}, "obj": "http://ncicb.nci.nih.gov/xml/owl/EVS/Thesaurus.owl#C12412"}, {"span": {"begin": 543, "end": 549}, "obj": "http://ncicb.nci.nih.gov/xml/owl/EVS/Thesaurus.owl#C12412"}, {"span": {"begin": 1262, "end": 1268}, "obj": "http://ncicb.nci.nih.gov/xml/owl/EVS/Thesaurus.owl#C12412"}, {"span": {"begin": 34, "end": 40}, "obj": "http://purl.bioontology.org/ontology/NDDF/006640"}, {"span": {"begin": 219, "end": 225}, "obj": "http://purl.bioontology.org/ontology/NDDF/006640"}, {"span": {"begin": 543, "end": 549}, "obj": "http://purl.bioontology.org/ontology/NDDF/006640"}, {"span": {"begin": 1262, "end": 1268}, "obj": "http://purl.bioontology.org/ontology/NDDF/006640"}, {"span": {"begin": 34, "end": 40}, "obj": "http://ncicb.nci.nih.gov/xml/owl/EVS/Thesaurus.owl#C23346"}, {"span": {"begin": 219, "end": 225}, "obj": "http://ncicb.nci.nih.gov/xml/owl/EVS/Thesaurus.owl#C23346"}, {"span": {"begin": 543, "end": 549}, "obj": "http://ncicb.nci.nih.gov/xml/owl/EVS/Thesaurus.owl#C23346"}, {"span": {"begin": 1262, "end": 1268}, "obj": "http://ncicb.nci.nih.gov/xml/owl/EVS/Thesaurus.owl#C23346"}, {"span": {"begin": 41, "end": 45}, "obj": "http://purl.org/sig/ont/fma/fma74402"}, {"span": {"begin": 181, "end": 185}, "obj": "http://purl.org/sig/ont/fma/fma74402"}, {"span": {"begin": 276, "end": 280}, "obj": "http://purl.org/sig/ont/fma/fma74402"}, {"span": {"begin": 467, "end": 471}, "obj": "http://purl.org/sig/ont/fma/fma74402"}, {"span": {"begin": 572, "end": 576}, "obj": "http://purl.org/sig/ont/fma/fma74402"}, {"span": {"begin": 1243, "end": 1247}, "obj": "http://purl.org/sig/ont/fma/fma74402"}, {"span": {"begin": 41, "end": 45}, "obj": "http://purl.bioontology.org/ontology/SNOMEDCT/67271001"}, {"span": {"begin": 181, "end": 185}, "obj": "http://purl.bioontology.org/ontology/SNOMEDCT/67271001"}, {"span": {"begin": 276, "end": 280}, "obj": "http://purl.bioontology.org/ontology/SNOMEDCT/67271001"}, {"span": {"begin": 467, "end": 471}, "obj": "http://purl.bioontology.org/ontology/SNOMEDCT/67271001"}, {"span": {"begin": 572, "end": 576}, "obj": "http://purl.bioontology.org/ontology/SNOMEDCT/67271001"}, {"span": {"begin": 1243, "end": 1247}, "obj": "http://purl.bioontology.org/ontology/SNOMEDCT/67271001"}, {"span": {"begin": 41, "end": 45}, "obj": "http://ncicb.nci.nih.gov/xml/owl/EVS/Thesaurus.owl#C45520"}, {"span": {"begin": 181, "end": 185}, "obj": "http://ncicb.nci.nih.gov/xml/owl/EVS/Thesaurus.owl#C45520"}, {"span": {"begin": 276, "end": 280}, "obj": "http://ncicb.nci.nih.gov/xml/owl/EVS/Thesaurus.owl#C45520"}, {"span": {"begin": 467, "end": 471}, "obj": "http://ncicb.nci.nih.gov/xml/owl/EVS/Thesaurus.owl#C45520"}, {"span": {"begin": 572, "end": 576}, "obj": "http://ncicb.nci.nih.gov/xml/owl/EVS/Thesaurus.owl#C45520"}, {"span": {"begin": 1243, "end": 1247}, "obj": "http://ncicb.nci.nih.gov/xml/owl/EVS/Thesaurus.owl#C45520"}, {"span": {"begin": 41, "end": 45}, "obj": "http://purl.obolibrary.org/obo/SO_0000704"}, {"span": {"begin": 181, "end": 185}, "obj": "http://purl.obolibrary.org/obo/SO_0000704"}, {"span": {"begin": 276, "end": 280}, "obj": "http://purl.obolibrary.org/obo/SO_0000704"}, {"span": {"begin": 467, "end": 471}, "obj": "http://purl.obolibrary.org/obo/SO_0000704"}, {"span": {"begin": 572, "end": 576}, "obj": "http://purl.obolibrary.org/obo/SO_0000704"}, {"span": {"begin": 1243, "end": 1247}, "obj": "http://purl.obolibrary.org/obo/SO_0000704"}, {"span": {"begin": 41, "end": 45}, "obj": "http://ncicb.nci.nih.gov/xml/owl/EVS/Thesaurus.owl#C16612"}, {"span": {"begin": 181, "end": 185}, "obj": "http://ncicb.nci.nih.gov/xml/owl/EVS/Thesaurus.owl#C16612"}, {"span": {"begin": 276, "end": 280}, "obj": "http://ncicb.nci.nih.gov/xml/owl/EVS/Thesaurus.owl#C16612"}, {"span": {"begin": 467, "end": 471}, "obj": "http://ncicb.nci.nih.gov/xml/owl/EVS/Thesaurus.owl#C16612"}, {"span": {"begin": 572, "end": 576}, "obj": "http://ncicb.nci.nih.gov/xml/owl/EVS/Thesaurus.owl#C16612"}, {"span": {"begin": 1243, "end": 1247}, "obj": "http://ncicb.nci.nih.gov/xml/owl/EVS/Thesaurus.owl#C16612"}, {"span": {"begin": 46, "end": 49}, "obj": "http://ncicb.nci.nih.gov/xml/owl/EVS/Thesaurus.owl#C97379"}, {"span": {"begin": 50, "end": 57}, "obj": "http://ncicb.nci.nih.gov/xml/owl/EVS/Thesaurus.owl#C97379"}, {"span": {"begin": 187, "end": 190}, "obj": "http://ncicb.nci.nih.gov/xml/owl/EVS/Thesaurus.owl#C97379"}, {"span": {"begin": 388, "end": 391}, "obj": "http://ncicb.nci.nih.gov/xml/owl/EVS/Thesaurus.owl#C97379"}, {"span": {"begin": 463, "end": 466}, "obj": "http://ncicb.nci.nih.gov/xml/owl/EVS/Thesaurus.owl#C97379"}, {"span": {"begin": 488, "end": 495}, "obj": "http://ncicb.nci.nih.gov/xml/owl/EVS/Thesaurus.owl#C97379"}, {"span": {"begin": 497, "end": 500}, "obj": "http://ncicb.nci.nih.gov/xml/owl/EVS/Thesaurus.owl#C97379"}, {"span": {"begin": 749, "end": 752}, "obj": "http://ncicb.nci.nih.gov/xml/owl/EVS/Thesaurus.owl#C97379"}, {"span": {"begin": 840, "end": 843}, "obj": "http://ncicb.nci.nih.gov/xml/owl/EVS/Thesaurus.owl#C97379"}, {"span": {"begin": 956, "end": 959}, "obj": "http://ncicb.nci.nih.gov/xml/owl/EVS/Thesaurus.owl#C97379"}, {"span": {"begin": 1111, "end": 1114}, "obj": "http://ncicb.nci.nih.gov/xml/owl/EVS/Thesaurus.owl#C97379"}, {"span": {"begin": 1218, "end": 1221}, "obj": "http://ncicb.nci.nih.gov/xml/owl/EVS/Thesaurus.owl#C97379"}, {"span": {"begin": 1222, "end": 1229}, "obj": "http://ncicb.nci.nih.gov/xml/owl/EVS/Thesaurus.owl#C97379"}, {"span": {"begin": 50, "end": 57}, "obj": "http://ncicb.nci.nih.gov/xml/owl/EVS/Thesaurus.owl#C97380"}, {"span": {"begin": 488, "end": 495}, "obj": "http://ncicb.nci.nih.gov/xml/owl/EVS/Thesaurus.owl#C97380"}, {"span": {"begin": 1222, "end": 1229}, "obj": "http://ncicb.nci.nih.gov/xml/owl/EVS/Thesaurus.owl#C97380"}, {"span": {"begin": 50, "end": 57}, "obj": "http://purl.obolibrary.org/obo/PR_000005050"}, {"span": {"begin": 488, "end": 495}, "obj": "http://purl.obolibrary.org/obo/PR_000005050"}, {"span": {"begin": 1222, "end": 1229}, "obj": "http://purl.obolibrary.org/obo/PR_000005050"}, {"span": {"begin": 61, "end": 65}, "obj": "http://purl.bioontology.org/ontology/MESH/D008168"}, {"span": {"begin": 128, "end": 132}, "obj": "http://purl.bioontology.org/ontology/MESH/D008168"}, {"span": {"begin": 699, "end": 703}, "obj": "http://purl.bioontology.org/ontology/MESH/D008168"}, {"span": {"begin": 827, "end": 831}, "obj": "http://purl.bioontology.org/ontology/MESH/D008168"}, {"span": {"begin": 61, "end": 65}, "obj": "http://purl.bioontology.org/ontology/OMIM/MTHU000106"}, {"span": {"begin": 128, "end": 132}, "obj": "http://purl.bioontology.org/ontology/OMIM/MTHU000106"}, {"span": {"begin": 699, "end": 703}, "obj": "http://purl.bioontology.org/ontology/OMIM/MTHU000106"}, {"span": {"begin": 827, "end": 831}, "obj": "http://purl.bioontology.org/ontology/OMIM/MTHU000106"}, {"span": {"begin": 61, "end": 65}, "obj": "http://ncicb.nci.nih.gov/xml/owl/EVS/Thesaurus.owl#C23402"}, {"span": {"begin": 128, "end": 132}, "obj": "http://ncicb.nci.nih.gov/xml/owl/EVS/Thesaurus.owl#C23402"}, {"span": {"begin": 699, "end": 703}, "obj": "http://ncicb.nci.nih.gov/xml/owl/EVS/Thesaurus.owl#C23402"}, {"span": {"begin": 827, "end": 831}, "obj": "http://ncicb.nci.nih.gov/xml/owl/EVS/Thesaurus.owl#C23402"}, {"span": {"begin": 61, "end": 65}, "obj": "http://purl.bioontology.org/ontology/OMIM/MTHU016106"}, {"span": {"begin": 128, "end": 132}, "obj": "http://purl.bioontology.org/ontology/OMIM/MTHU016106"}, {"span": {"begin": 699, "end": 703}, "obj": "http://purl.bioontology.org/ontology/OMIM/MTHU016106"}, {"span": {"begin": 827, "end": 831}, "obj": "http://purl.bioontology.org/ontology/OMIM/MTHU016106"}, {"span": {"begin": 61, "end": 65}, "obj": "http://ncicb.nci.nih.gov/xml/owl/EVS/Thesaurus.owl#C12468"}, {"span": {"begin": 128, "end": 132}, "obj": "http://ncicb.nci.nih.gov/xml/owl/EVS/Thesaurus.owl#C12468"}, {"span": {"begin": 699, "end": 703}, "obj": "http://ncicb.nci.nih.gov/xml/owl/EVS/Thesaurus.owl#C12468"}, {"span": {"begin": 827, "end": 831}, "obj": "http://ncicb.nci.nih.gov/xml/owl/EVS/Thesaurus.owl#C12468"}, {"span": {"begin": 61, "end": 65}, "obj": "http://purl.obolibrary.org/obo/UBERON_0002048"}, {"span": {"begin": 128, "end": 132}, "obj": "http://purl.obolibrary.org/obo/UBERON_0002048"}, {"span": {"begin": 699, "end": 703}, "obj": "http://purl.obolibrary.org/obo/UBERON_0002048"}, {"span": {"begin": 827, "end": 831}, "obj": "http://purl.obolibrary.org/obo/UBERON_0002048"}, {"span": {"begin": 61, "end": 65}, "obj": "http://purl.obolibrary.org/obo/UBERON_0002048"}, {"span": {"begin": 128, "end": 132}, "obj": "http://purl.obolibrary.org/obo/UBERON_0002048"}, {"span": {"begin": 699, "end": 703}, "obj": "http://purl.obolibrary.org/obo/UBERON_0002048"}, {"span": {"begin": 827, "end": 831}, "obj": "http://purl.obolibrary.org/obo/UBERON_0002048"}, {"span": {"begin": 61, "end": 65}, "obj": "http://purl.org/sig/ont/fma/fma7195"}, {"span": {"begin": 128, "end": 132}, "obj": "http://purl.org/sig/ont/fma/fma7195"}, {"span": {"begin": 699, "end": 703}, "obj": "http://purl.org/sig/ont/fma/fma7195"}, {"span": {"begin": 827, "end": 831}, "obj": "http://purl.org/sig/ont/fma/fma7195"}, {"span": {"begin": 61, "end": 65}, "obj": "http://purl.bioontology.org/ontology/SNOMEDCT/39607008"}, {"span": {"begin": 128, "end": 132}, "obj": "http://purl.bioontology.org/ontology/SNOMEDCT/39607008"}, {"span": {"begin": 699, "end": 703}, "obj": "http://purl.bioontology.org/ontology/SNOMEDCT/39607008"}, {"span": {"begin": 827, "end": 831}, "obj": "http://purl.bioontology.org/ontology/SNOMEDCT/39607008"}, {"span": {"begin": 77, "end": 84}, "obj": "http://purl.bioontology.org/ontology/MESH/D000074285"}, {"span": {"begin": 143, "end": 150}, "obj": "http://purl.bioontology.org/ontology/MESH/D000074285"}, {"span": {"begin": 1209, "end": 1216}, "obj": "http://purl.bioontology.org/ontology/MESH/D000074285"}, {"span": {"begin": 108, "end": 119}, "obj": "http://ncicb.nci.nih.gov/xml/owl/EVS/Thesaurus.owl#C48834"}, {"span": {"begin": 128, "end": 139}, "obj": "http://purl.bioontology.org/ontology/MEDLINEPLUS/C0242379"}, {"span": {"begin": 699, "end": 710}, "obj": "http://purl.bioontology.org/ontology/MEDLINEPLUS/C0242379"}, {"span": {"begin": 827, "end": 838}, "obj": "http://purl.bioontology.org/ontology/MEDLINEPLUS/C0242379"}, {"span": {"begin": 128, "end": 139}, "obj": "http://ncicb.nci.nih.gov/xml/owl/EVS/Thesaurus.owl#C4878"}, {"span": {"begin": 699, "end": 710}, "obj": "http://ncicb.nci.nih.gov/xml/owl/EVS/Thesaurus.owl#C4878"}, {"span": {"begin": 827, "end": 838}, "obj": "http://ncicb.nci.nih.gov/xml/owl/EVS/Thesaurus.owl#C4878"}, {"span": {"begin": 128, "end": 139}, "obj": "http://purl.bioontology.org/ontology/MEDDRA/10025044"}, {"span": {"begin": 699, "end": 710}, "obj": "http://purl.bioontology.org/ontology/MEDDRA/10025044"}, {"span": {"begin": 827, "end": 838}, "obj": "http://purl.bioontology.org/ontology/MEDDRA/10025044"}, {"span": {"begin": 128, "end": 139}, "obj": "http://purl.bioontology.org/ontology/OMIM/211980"}, {"span": {"begin": 699, "end": 710}, "obj": "http://purl.bioontology.org/ontology/OMIM/211980"}, {"span": {"begin": 827, "end": 838}, "obj": "http://purl.bioontology.org/ontology/OMIM/211980"}, {"span": {"begin": 175, "end": 185}, "obj": "http://purl.bioontology.org/ontology/SNOMEDCT/82256003"}, {"span": {"begin": 270, "end": 280}, "obj": "http://purl.bioontology.org/ontology/SNOMEDCT/82256003"}, {"span": {"begin": 175, "end": 180}, "obj": "http://ncicb.nci.nih.gov/xml/owl/EVS/Thesaurus.owl#C14225"}, {"span": {"begin": 270, "end": 275}, "obj": "http://ncicb.nci.nih.gov/xml/owl/EVS/Thesaurus.owl#C14225"}, {"span": {"begin": 324, "end": 329}, "obj": "http://ncicb.nci.nih.gov/xml/owl/EVS/Thesaurus.owl#C14225"}, {"span": {"begin": 606, "end": 611}, "obj": "http://ncicb.nci.nih.gov/xml/owl/EVS/Thesaurus.owl#C14225"}, {"span": {"begin": 175, "end": 180}, "obj": "http://purl.bioontology.org/ontology/STY/T016"}, {"span": {"begin": 270, "end": 275}, "obj": "http://purl.bioontology.org/ontology/STY/T016"}, {"span": {"begin": 324, "end": 329}, "obj": "http://purl.bioontology.org/ontology/STY/T016"}, {"span": {"begin": 606, "end": 611}, "obj": "http://purl.bioontology.org/ontology/STY/T016"}, {"span": {"begin": 175, "end": 180}, "obj": "http://purl.bioontology.org/ontology/STY/T016"}, {"span": {"begin": 270, "end": 275}, "obj": "http://purl.bioontology.org/ontology/STY/T016"}, {"span": {"begin": 324, "end": 329}, "obj": "http://purl.bioontology.org/ontology/STY/T016"}, {"span": {"begin": 606, "end": 611}, "obj": "http://purl.bioontology.org/ontology/STY/T016"}, {"span": {"begin": 175, "end": 180}, "obj": "http://purl.bioontology.org/ontology/STY/T016"}, {"span": {"begin": 270, "end": 275}, "obj": "http://purl.bioontology.org/ontology/STY/T016"}, {"span": {"begin": 324, "end": 329}, "obj": "http://purl.bioontology.org/ontology/STY/T016"}, {"span": {"begin": 606, "end": 611}, "obj": "http://purl.bioontology.org/ontology/STY/T016"}, {"span": {"begin": 175, "end": 180}, "obj": "http://purl.bioontology.org/ontology/STY/T016"}, {"span": {"begin": 270, "end": 275}, "obj": "http://purl.bioontology.org/ontology/STY/T016"}, {"span": {"begin": 324, "end": 329}, "obj": "http://purl.bioontology.org/ontology/STY/T016"}, {"span": {"begin": 606, "end": 611}, "obj": "http://purl.bioontology.org/ontology/STY/T016"}, {"span": {"begin": 175, "end": 180}, "obj": "http://purl.bioontology.org/ontology/STY/T016"}, {"span": {"begin": 270, "end": 275}, "obj": "http://purl.bioontology.org/ontology/STY/T016"}, {"span": {"begin": 324, "end": 329}, "obj": "http://purl.bioontology.org/ontology/STY/T016"}, {"span": {"begin": 606, "end": 611}, "obj": "http://purl.bioontology.org/ontology/STY/T016"}, {"span": {"begin": 175, "end": 180}, "obj": "http://purl.bioontology.org/ontology/STY/T016"}, {"span": {"begin": 270, "end": 275}, "obj": "http://purl.bioontology.org/ontology/STY/T016"}, {"span": {"begin": 324, "end": 329}, "obj": "http://purl.bioontology.org/ontology/STY/T016"}, {"span": {"begin": 606, "end": 611}, "obj": "http://purl.bioontology.org/ontology/STY/T016"}, {"span": {"begin": 175, "end": 180}, "obj": "http://purl.bioontology.org/ontology/STY/T016"}, {"span": {"begin": 270, "end": 275}, "obj": "http://purl.bioontology.org/ontology/STY/T016"}, {"span": {"begin": 324, "end": 329}, "obj": "http://purl.bioontology.org/ontology/STY/T016"}, {"span": {"begin": 606, "end": 611}, "obj": "http://purl.bioontology.org/ontology/STY/T016"}, {"span": {"begin": 175, "end": 180}, "obj": "http://purl.bioontology.org/ontology/STY/T016"}, {"span": {"begin": 270, "end": 275}, "obj": "http://purl.bioontology.org/ontology/STY/T016"}, {"span": {"begin": 324, "end": 329}, "obj": "http://purl.bioontology.org/ontology/STY/T016"}, {"span": {"begin": 606, "end": 611}, "obj": "http://purl.bioontology.org/ontology/STY/T016"}, {"span": {"begin": 175, "end": 180}, "obj": "http://purl.bioontology.org/ontology/STY/T016"}, {"span": {"begin": 270, "end": 275}, "obj": "http://purl.bioontology.org/ontology/STY/T016"}, {"span": {"begin": 324, "end": 329}, "obj": "http://purl.bioontology.org/ontology/STY/T016"}, {"span": {"begin": 606, "end": 611}, "obj": "http://purl.bioontology.org/ontology/STY/T016"}, {"span": {"begin": 175, "end": 180}, "obj": "http://purl.obolibrary.org/obo/NCBITaxon_9606"}, {"span": {"begin": 270, "end": 275}, "obj": "http://purl.obolibrary.org/obo/NCBITaxon_9606"}, {"span": {"begin": 324, "end": 329}, "obj": "http://purl.obolibrary.org/obo/NCBITaxon_9606"}, {"span": {"begin": 606, "end": 611}, "obj": "http://purl.obolibrary.org/obo/NCBITaxon_9606"}, {"span": {"begin": 175, "end": 180}, "obj": "http://purl.obolibrary.org/obo/NCBITaxon_9606"}, {"span": {"begin": 270, "end": 275}, "obj": "http://purl.obolibrary.org/obo/NCBITaxon_9606"}, {"span": {"begin": 324, "end": 329}, "obj": "http://purl.obolibrary.org/obo/NCBITaxon_9606"}, {"span": {"begin": 606, "end": 611}, "obj": "http://purl.obolibrary.org/obo/NCBITaxon_9606"}, {"span": {"begin": 206, "end": 215}, "obj": "http://ncicb.nci.nih.gov/xml/owl/EVS/Thesaurus.owl#C18888"}, {"span": {"begin": 523, "end": 532}, "obj": "http://ncicb.nci.nih.gov/xml/owl/EVS/Thesaurus.owl#C18888"}, {"span": {"begin": 585, "end": 594}, "obj": "http://ncicb.nci.nih.gov/xml/owl/EVS/Thesaurus.owl#C18888"}, {"span": {"begin": 206, "end": 215}, "obj": "http://ncicb.nci.nih.gov/xml/owl/EVS/Thesaurus.owl#C18966"}, {"span": {"begin": 523, "end": 532}, "obj": "http://ncicb.nci.nih.gov/xml/owl/EVS/Thesaurus.owl#C18966"}, {"span": {"begin": 585, "end": 594}, "obj": "http://ncicb.nci.nih.gov/xml/owl/EVS/Thesaurus.owl#C18966"}, {"span": {"begin": 245, "end": 252}, "obj": "http://ncicb.nci.nih.gov/xml/owl/EVS/Thesaurus.owl#C39769"}, {"span": {"begin": 256, "end": 261}, "obj": "http://ncicb.nci.nih.gov/xml/owl/EVS/Thesaurus.owl#C37925"}, {"span": {"begin": 362, "end": 367}, "obj": "http://ncicb.nci.nih.gov/xml/owl/EVS/Thesaurus.owl#C37925"}, {"span": {"begin": 256, "end": 261}, "obj": "http://ncicb.nci.nih.gov/xml/owl/EVS/Thesaurus.owl#C41163"}, {"span": {"begin": 362, "end": 367}, "obj": "http://ncicb.nci.nih.gov/xml/owl/EVS/Thesaurus.owl#C41163"}, {"span": {"begin": 256, "end": 261}, "obj": "http://purl.bioontology.org/ontology/SNOMEDCT/47308002"}, {"span": {"begin": 362, "end": 367}, "obj": "http://purl.bioontology.org/ontology/SNOMEDCT/47308002"}, {"span": {"begin": 264, "end": 269}, "obj": "http://ncicb.nci.nih.gov/xml/owl/EVS/Thesaurus.owl#C25586"}, {"span": {"begin": 296, "end": 308}, "obj": "http://purl.obolibrary.org/obo/OBI_0000164"}, {"span": {"begin": 296, "end": 308}, "obj": "http://ncicb.nci.nih.gov/xml/owl/EVS/Thesaurus.owl#C15727"}, {"span": {"begin": 301, "end": 308}, "obj": "http://ncicb.nci.nih.gov/xml/owl/EVS/Thesaurus.owl#C15727"}, {"span": {"begin": 296, "end": 300}, "obj": "http://ncicb.nci.nih.gov/xml/owl/EVS/Thesaurus.owl#C324"}, {"span": {"begin": 357, "end": 361}, "obj": "http://ncicb.nci.nih.gov/xml/owl/EVS/Thesaurus.owl#C324"}, {"span": {"begin": 301, "end": 308}, "obj": "http://purl.bioontology.org/ontology/SNOMEDCT/264366000"}, {"span": {"begin": 301, "end": 308}, "obj": "http://ncicb.nci.nih.gov/xml/owl/EVS/Thesaurus.owl#C45521"}, {"span": {"begin": 301, "end": 308}, "obj": "http://ncicb.nci.nih.gov/xml/owl/EVS/Thesaurus.owl#C16223"}, {"span": {"begin": 301, "end": 308}, "obj": "http://purl.bioontology.org/ontology/MESH/D007990"}, {"span": {"begin": 309, "end": 316}, "obj": "http://ncicb.nci.nih.gov/xml/owl/EVS/Thesaurus.owl#C42885"}, {"span": {"begin": 650, "end": 657}, "obj": "http://ncicb.nci.nih.gov/xml/owl/EVS/Thesaurus.owl#C42885"}, {"span": {"begin": 309, "end": 316}, "obj": "http://ncicb.nci.nih.gov/xml/owl/EVS/Thesaurus.owl#C73924"}, {"span": {"begin": 650, "end": 657}, "obj": "http://ncicb.nci.nih.gov/xml/owl/EVS/Thesaurus.owl#C73924"}, {"span": {"begin": 309, "end": 316}, "obj": "http://ncicb.nci.nih.gov/xml/owl/EVS/Thesaurus.owl#C69271"}, {"span": {"begin": 650, "end": 657}, "obj": "http://ncicb.nci.nih.gov/xml/owl/EVS/Thesaurus.owl#C69271"}, {"span": {"begin": 309, "end": 316}, "obj": "http://ncicb.nci.nih.gov/xml/owl/EVS/Thesaurus.owl#C81197"}, {"span": {"begin": 650, "end": 657}, "obj": "http://ncicb.nci.nih.gov/xml/owl/EVS/Thesaurus.owl#C81197"}, {"span": {"begin": 330, "end": 336}, "obj": "http://purl.bioontology.org/ontology/SNOMEDCT/112130006"}, {"span": {"begin": 330, "end": 336}, "obj": "http://purl.obolibrary.org/obo/CL_0000236"}, {"span": {"begin": 330, "end": 336}, "obj": "http://ncicb.nci.nih.gov/xml/owl/EVS/Thesaurus.owl#C12474"}, {"span": {"begin": 332, "end": 341}, "obj": "http://purl.obolibrary.org/obo/CLO_0000031"}, {"span": {"begin": 332, "end": 341}, "obj": "http://purl.bioontology.org/ontology/MESH/D002460"}, {"span": {"begin": 619, "end": 629}, "obj": "http://purl.bioontology.org/ontology/MESH/D002460"}, {"span": {"begin": 332, "end": 341}, "obj": "http://ncicb.nci.nih.gov/xml/owl/EVS/Thesaurus.owl#C16403"}, {"span": {"begin": 332, "end": 336}, "obj": "http://purl.bioontology.org/ontology/STY/T025"}, {"span": {"begin": 619, "end": 623}, "obj": "http://purl.bioontology.org/ontology/STY/T025"}, {"span": {"begin": 332, "end": 336}, "obj": "http://purl.bioontology.org/ontology/STY/T025"}, {"span": {"begin": 619, "end": 623}, "obj": "http://purl.bioontology.org/ontology/STY/T025"}, {"span": {"begin": 332, "end": 336}, "obj": "http://purl.bioontology.org/ontology/STY/T025"}, {"span": {"begin": 619, "end": 623}, "obj": "http://purl.bioontology.org/ontology/STY/T025"}, {"span": {"begin": 332, "end": 336}, "obj": "http://purl.bioontology.org/ontology/STY/T025"}, {"span": {"begin": 619, "end": 623}, "obj": "http://purl.bioontology.org/ontology/STY/T025"}, {"span": {"begin": 332, "end": 336}, "obj": "http://purl.bioontology.org/ontology/STY/T025"}, {"span": {"begin": 619, "end": 623}, "obj": "http://purl.bioontology.org/ontology/STY/T025"}, {"span": {"begin": 332, "end": 336}, "obj": "http://purl.bioontology.org/ontology/STY/T025"}, {"span": {"begin": 619, "end": 623}, "obj": "http://purl.bioontology.org/ontology/STY/T025"}, {"span": {"begin": 332, "end": 336}, "obj": "http://purl.bioontology.org/ontology/STY/T025"}, {"span": {"begin": 619, "end": 623}, "obj": "http://purl.bioontology.org/ontology/STY/T025"}, {"span": {"begin": 332, "end": 336}, "obj": "http://purl.bioontology.org/ontology/STY/T025"}, {"span": {"begin": 619, "end": 623}, "obj": "http://purl.bioontology.org/ontology/STY/T025"}, {"span": {"begin": 332, "end": 336}, "obj": "http://purl.bioontology.org/ontology/STY/T025"}, {"span": {"begin": 619, "end": 623}, "obj": "http://purl.bioontology.org/ontology/STY/T025"}, {"span": {"begin": 332, "end": 336}, "obj": "http://ncicb.nci.nih.gov/xml/owl/EVS/Thesaurus.owl#C49867"}, {"span": {"begin": 619, "end": 623}, "obj": "http://ncicb.nci.nih.gov/xml/owl/EVS/Thesaurus.owl#C49867"}, {"span": {"begin": 332, "end": 336}, "obj": "http://purl.obolibrary.org/obo/GO_0005623"}, {"span": {"begin": 619, "end": 623}, "obj": "http://purl.obolibrary.org/obo/GO_0005623"}, {"span": {"begin": 332, "end": 336}, "obj": "http://ncicb.nci.nih.gov/xml/owl/EVS/Thesaurus.owl#C12508"}, {"span": {"begin": 619, "end": 623}, "obj": "http://ncicb.nci.nih.gov/xml/owl/EVS/Thesaurus.owl#C12508"}, {"span": {"begin": 332, "end": 336}, "obj": "http://ncicb.nci.nih.gov/xml/owl/EVS/Thesaurus.owl#C23442"}, {"span": {"begin": 619, "end": 623}, "obj": "http://ncicb.nci.nih.gov/xml/owl/EVS/Thesaurus.owl#C23442"}, {"span": {"begin": 332, "end": 336}, "obj": "http://purl.org/sig/ont/fma/fma68646"}, {"span": {"begin": 619, "end": 623}, "obj": "http://purl.org/sig/ont/fma/fma68646"}, {"span": {"begin": 332, "end": 336}, "obj": "http://purl.obolibrary.org/obo/CL_0000000"}, {"span": {"begin": 619, "end": 623}, "obj": "http://purl.obolibrary.org/obo/CL_0000000"}, {"span": {"begin": 332, "end": 336}, "obj": "http://purl.obolibrary.org/obo/CL_0000000"}, {"span": {"begin": 619, "end": 623}, "obj": "http://purl.obolibrary.org/obo/CL_0000000"}, {"span": {"begin": 332, "end": 336}, "obj": "http://ncicb.nci.nih.gov/xml/owl/EVS/Thesaurus.owl#C60787"}, {"span": {"begin": 619, "end": 623}, "obj": "http://ncicb.nci.nih.gov/xml/owl/EVS/Thesaurus.owl#C60787"}, {"span": {"begin": 332, "end": 336}, "obj": "http://ncicb.nci.nih.gov/xml/owl/EVS/Thesaurus.owl#C48694"}, {"span": {"begin": 619, "end": 623}, "obj": "http://ncicb.nci.nih.gov/xml/owl/EVS/Thesaurus.owl#C48694"}, {"span": {"begin": 332, "end": 336}, "obj": "http://purl.bioontology.org/ontology/MESH/D002477"}, {"span": {"begin": 619, "end": 623}, "obj": "http://purl.bioontology.org/ontology/MESH/D002477"}, {"span": {"begin": 395, "end": 401}, "obj": "http://ncicb.nci.nih.gov/xml/owl/EVS/Thesaurus.owl#C54117"}, {"span": {"begin": 406, "end": 412}, "obj": "http://ncicb.nci.nih.gov/xml/owl/EVS/Thesaurus.owl#C49060"}, {"span": {"begin": 427, "end": 435}, "obj": "http://ncicb.nci.nih.gov/xml/owl/EVS/Thesaurus.owl#C43465"}, {"span": {"begin": 427, "end": 435}, "obj": "http://ncicb.nci.nih.gov/xml/owl/EVS/Thesaurus.owl#C89252"}, {"span": {"begin": 427, "end": 435}, "obj": "http://ncicb.nci.nih.gov/xml/owl/EVS/Thesaurus.owl#C13299"}, {"span": {"begin": 427, "end": 435}, "obj": "http://ncicb.nci.nih.gov/xml/owl/EVS/Thesaurus.owl#C25673"}, {"span": {"begin": 427, "end": 435}, "obj": "http://ncicb.nci.nih.gov/xml/owl/EVS/Thesaurus.owl#C45374"}, {"span": {"begin": 427, "end": 435}, "obj": "http://purl.obolibrary.org/obo/SO_0000001"}, {"span": {"begin": 475, "end": 484}, "obj": "http://purl.bioontology.org/ontology/SNOMEDCT/20323000"}, {"span": {"begin": 475, "end": 484}, "obj": "http://ncicb.nci.nih.gov/xml/owl/EVS/Thesaurus.owl#C49034"}, {"span": {"begin": 501, "end": 505}, "obj": "http://ncicb.nci.nih.gov/xml/owl/EVS/Thesaurus.owl#C813"}, {"span": {"begin": 501, "end": 505}, "obj": "http://purl.org/sig/ont/fma/fma67122"}, {"span": {"begin": 536, "end": 542}, "obj": "http://purl.bioontology.org/ontology/OMIM/MTHU002946"}, {"span": {"begin": 536, "end": 542}, "obj": "http://ncicb.nci.nih.gov/xml/owl/EVS/Thesaurus.owl#C74593"}, {"span": {"begin": 536, "end": 542}, "obj": "http://ncicb.nci.nih.gov/xml/owl/EVS/Thesaurus.owl#C140746"}, {"span": {"begin": 536, "end": 542}, "obj": "http://ncicb.nci.nih.gov/xml/owl/EVS/Thesaurus.owl#C78727"}, {"span": {"begin": 536, "end": 542}, "obj": "http://ncicb.nci.nih.gov/xml/owl/EVS/Thesaurus.owl#C121439"}, {"span": {"begin": 536, "end": 542}, "obj": "http://ncicb.nci.nih.gov/xml/owl/EVS/Thesaurus.owl#C14165"}, {"span": {"begin": 536, "end": 542}, "obj": "http://ncicb.nci.nih.gov/xml/owl/EVS/Thesaurus.owl#C48554"}, {"span": {"begin": 536, "end": 542}, "obj": "http://purl.bioontology.org/ontology/SNOMEDCT/17621005"}, {"span": {"begin": 550, "end": 556}, "obj": "http://purl.bioontology.org/ontology/STY/T024"}, {"span": {"begin": 550, "end": 556}, "obj": "http://purl.bioontology.org/ontology/STY/T024"}, {"span": {"begin": 550, "end": 556}, "obj": "http://purl.bioontology.org/ontology/STY/T024"}, {"span": {"begin": 550, "end": 556}, "obj": "http://purl.bioontology.org/ontology/STY/T024"}, {"span": {"begin": 550, "end": 556}, "obj": "http://purl.bioontology.org/ontology/STY/T024"}, {"span": {"begin": 550, "end": 556}, "obj": "http://purl.bioontology.org/ontology/STY/T024"}, {"span": {"begin": 550, "end": 556}, "obj": "http://purl.bioontology.org/ontology/STY/T024"}, {"span": {"begin": 550, "end": 556}, "obj": "http://purl.bioontology.org/ontology/STY/T024"}, {"span": {"begin": 550, "end": 556}, "obj": "http://purl.bioontology.org/ontology/STY/T024"}, {"span": {"begin": 550, "end": 556}, "obj": "http://purl.bioontology.org/ontology/MESH/D014024"}, {"span": {"begin": 682, "end": 689}, "obj": "http://purl.bioontology.org/ontology/MESH/D014024"}, {"span": {"begin": 550, "end": 556}, "obj": "http://ncicb.nci.nih.gov/xml/owl/EVS/Thesaurus.owl#C33177"}, {"span": {"begin": 550, "end": 556}, "obj": "http://purl.obolibrary.org/obo/UBERON_0000479"}, {"span": {"begin": 550, "end": 556}, "obj": "http://purl.org/sig/ont/fma/fma9637"}, {"span": {"begin": 550, "end": 556}, "obj": "http://ncicb.nci.nih.gov/xml/owl/EVS/Thesaurus.owl#C12801"}, {"span": {"begin": 682, "end": 689}, "obj": "http://ncicb.nci.nih.gov/xml/owl/EVS/Thesaurus.owl#C12801"}, {"span": {"begin": 550, "end": 556}, "obj": "http://ncicb.nci.nih.gov/xml/owl/EVS/Thesaurus.owl#C12801"}, {"span": {"begin": 550, "end": 556}, "obj": "http://ncicb.nci.nih.gov/xml/owl/EVS/Thesaurus.owl#C23732"}, {"span": {"begin": 612, "end": 623}, "obj": "http://purl.bioontology.org/ontology/SNOMEDCT/252987004"}, {"span": {"begin": 612, "end": 618}, "obj": "http://purl.bioontology.org/ontology/SNOMEDCT/108369006"}, {"span": {"begin": 933, "end": 939}, "obj": "http://purl.bioontology.org/ontology/SNOMEDCT/108369006"}, {"span": {"begin": 624, "end": 629}, "obj": "http://ncicb.nci.nih.gov/xml/owl/EVS/Thesaurus.owl#C13803"}, {"span": {"begin": 634, "end": 641}, "obj": "http://ncicb.nci.nih.gov/xml/owl/EVS/Thesaurus.owl#C25251"}, {"span": {"begin": 819, "end": 826}, "obj": "http://ncicb.nci.nih.gov/xml/owl/EVS/Thesaurus.owl#C25251"}, {"span": {"begin": 715, "end": 723}, "obj": "http://ncicb.nci.nih.gov/xml/owl/EVS/Thesaurus.owl#C25500"}, {"span": {"begin": 728, "end": 740}, "obj": "http://ncicb.nci.nih.gov/xml/owl/EVS/Thesaurus.owl#C103376"}, {"span": {"begin": 728, "end": 740}, "obj": "http://ncicb.nci.nih.gov/xml/owl/EVS/Thesaurus.owl#C25648"}, {"span": {"begin": 728, "end": 740}, "obj": "http://ncicb.nci.nih.gov/xml/owl/EVS/Thesaurus.owl#C43570"}, {"span": {"begin": 728, "end": 740}, "obj": "http://ncicb.nci.nih.gov/xml/owl/EVS/Thesaurus.owl#C42727"}, {"span": {"begin": 728, "end": 740}, "obj": "http://ncicb.nci.nih.gov/xml/owl/EVS/Thesaurus.owl#C71472"}, {"span": {"begin": 728, "end": 740}, "obj": "http://purl.bioontology.org/ontology/SNOMEDCT/263498003"}, {"span": {"begin": 776, "end": 788}, "obj": "http://ncicb.nci.nih.gov/xml/owl/EVS/Thesaurus.owl#C25610"}, {"span": {"begin": 920, "end": 932}, "obj": "http://ncicb.nci.nih.gov/xml/owl/EVS/Thesaurus.owl#C25610"}, {"span": {"begin": 776, "end": 788}, "obj": "http://ncicb.nci.nih.gov/xml/owl/EVS/Thesaurus.owl#C18189"}, {"span": {"begin": 920, "end": 932}, "obj": "http://ncicb.nci.nih.gov/xml/owl/EVS/Thesaurus.owl#C18189"}, {"span": {"begin": 789, "end": 804}, "obj": "http://ncicb.nci.nih.gov/xml/owl/EVS/Thesaurus.owl#C25447"}, {"span": {"begin": 899, "end": 916}, "obj": "http://purl.bioontology.org/ontology/SNOMEDCT/263541007"}, {"span": {"begin": 899, "end": 911}, "obj": "http://ncicb.nci.nih.gov/xml/owl/EVS/Thesaurus.owl#C25526"}, {"span": {"begin": 912, "end": 916}, "obj": "http://purl.bioontology.org/ontology/SNOMEDCT/410656007"}, {"span": {"begin": 912, "end": 916}, "obj": "http://ncicb.nci.nih.gov/xml/owl/EVS/Thesaurus.owl#C25284"}, {"span": {"begin": 940, "end": 945}, "obj": "http://purl.bioontology.org/ontology/SNOMEDCT/258214002"}, {"span": {"begin": 940, "end": 945}, "obj": "http://ncicb.nci.nih.gov/xml/owl/EVS/Thesaurus.owl#C16899"}, {"span": {"begin": 940, "end": 945}, "obj": "http://ncicb.nci.nih.gov/xml/owl/EVS/Thesaurus.owl#C48308"}, {"span": {"begin": 940, "end": 945}, "obj": "http://ncicb.nci.nih.gov/xml/owl/EVS/Thesaurus.owl#C25257"}, {"span": {"begin": 975, "end": 983}, "obj": "http://ncicb.nci.nih.gov/xml/owl/EVS/Thesaurus.owl#C25599"}, {"span": {"begin": 1003, "end": 1024}, "obj": "http://ncicb.nci.nih.gov/xml/owl/EVS/Thesaurus.owl#C14167"}, {"span": {"begin": 1003, "end": 1024}, "obj": "http://purl.bioontology.org/ontology/SNOMEDCT/263843001"}, {"span": {"begin": 1010, "end": 1024}, "obj": "http://ncicb.nci.nih.gov/xml/owl/EVS/Thesaurus.owl#C16399"}, {"span": {"begin": 1060, "end": 1074}, "obj": "http://ncicb.nci.nih.gov/xml/owl/EVS/Thesaurus.owl#C16399"}, {"span": {"begin": 1041, "end": 1045}, "obj": "http://purl.bioontology.org/ontology/SNOMEDCT/20572008"}, {"span": {"begin": 1041, "end": 1045}, "obj": "http://ncicb.nci.nih.gov/xml/owl/EVS/Thesaurus.owl#C157663"}, {"span": {"begin": 1041, "end": 1045}, "obj": "http://ncicb.nci.nih.gov/xml/owl/EVS/Thesaurus.owl#C128793"}, {"span": {"begin": 1041, "end": 1045}, "obj": "http://ncicb.nci.nih.gov/xml/owl/EVS/Thesaurus.owl#C70592"}, {"span": {"begin": 1049, "end": 1074}, "obj": "http://purl.bioontology.org/ontology/SNOMEDCT/384812005"}, {"span": {"begin": 1049, "end": 1074}, "obj": "http://ncicb.nci.nih.gov/xml/owl/EVS/Thesaurus.owl#C14162"}, {"span": {"begin": 1049, "end": 1059}, "obj": "http://ncicb.nci.nih.gov/xml/owl/EVS/Thesaurus.owl#C125256"}, {"span": {"begin": 1049, "end": 1059}, "obj": "http://ncicb.nci.nih.gov/xml/owl/EVS/Thesaurus.owl#C61376"}, {"span": {"begin": 1049, "end": 1059}, "obj": "http://ncicb.nci.nih.gov/xml/owl/EVS/Thesaurus.owl#C129951"}, {"span": {"begin": 1098, "end": 1107}, "obj": "http://purl.bioontology.org/ontology/MESH/D015994"}, {"span": {"begin": 1098, "end": 1107}, "obj": "http://ncicb.nci.nih.gov/xml/owl/EVS/Thesaurus.owl#C16726"}, {"span": {"begin": 1144, "end": 1150}, "obj": "http://ncicb.nci.nih.gov/xml/owl/EVS/Thesaurus.owl#C25227"}, {"span": {"begin": 1167, "end": 1175}, "obj": "http://ncicb.nci.nih.gov/xml/owl/EVS/Thesaurus.owl#C16960"}, {"span": {"begin": 1340, "end": 1348}, "obj": "http://ncicb.nci.nih.gov/xml/owl/EVS/Thesaurus.owl#C16960"}, {"span": {"begin": 1167, "end": 1175}, "obj": "http://purl.bioontology.org/ontology/MESH/D010361"}, {"span": {"begin": 1340, "end": 1348}, "obj": "http://purl.bioontology.org/ontology/MESH/D010361"}, {"span": {"begin": 1180, "end": 1185}, "obj": "http://ncicb.nci.nih.gov/xml/owl/EVS/Thesaurus.owl#C63003"}, {"span": {"begin": 1315, "end": 1322}, "obj": "http://ncicb.nci.nih.gov/xml/owl/EVS/Thesaurus.owl#C63003"}, {"span": {"begin": 1180, "end": 1185}, "obj": "http://purl.bioontology.org/ontology/MESH/D012906"}, {"span": {"begin": 1180, "end": 1185}, "obj": "http://ncicb.nci.nih.gov/xml/owl/EVS/Thesaurus.owl#C829"}, {"span": {"begin": 1180, "end": 1185}, "obj": "http://purl.bioontology.org/ontology/SNOMEDCT/64197008"}, {"span": {"begin": 1205, "end": 1209}, "obj": "http://ncicb.nci.nih.gov/xml/owl/EVS/Thesaurus.owl#C25594"}, {"span": {"begin": 1269, "end": 1275}, "obj": "http://ncicb.nci.nih.gov/xml/owl/EVS/Thesaurus.owl#C79273"}, {"span": {"begin": 1269, "end": 1275}, "obj": "http://ncicb.nci.nih.gov/xml/owl/EVS/Thesaurus.owl#C45290"}, {"span": {"begin": 1269, "end": 1275}, "obj": "http://purl.bioontology.org/ontology/SNOMEDCT/35359004"}, {"span": {"begin": 1269, "end": 1275}, "obj": "http://ncicb.nci.nih.gov/xml/owl/EVS/Thesaurus.owl#C25173"}, {"span": {"begin": 1269, "end": 1275}, "obj": "http://purl.bioontology.org/ontology/MESH/D005190"}, {"span": {"begin": 1315, "end": 1322}, "obj": "http://ncicb.nci.nih.gov/xml/owl/EVS/Thesaurus.owl#C17934"}, {"span": {"begin": 1315, "end": 1322}, "obj": "http://purl.bioontology.org/ontology/MEDLINEPLUS/C0037369"}, {"span": {"begin": 1315, "end": 1322}, "obj": "http://ncicb.nci.nih.gov/xml/owl/EVS/Thesaurus.owl#C154329"}, {"span": {"begin": 1315, "end": 1322}, "obj": "http://purl.bioontology.org/ontology/MESH/D012907"}, {"span": {"begin": 1323, "end": 1329}, "obj": "http://purl.bioontology.org/ontology/MESH/D006184"}, {"span": {"begin": 1323, "end": 1329}, "obj": "http://purl.bioontology.org/ontology/SNOMEDCT/363898005"}, {"span": {"begin": 1358, "end": 1365}, "obj": "http://ncicb.nci.nih.gov/xml/owl/EVS/Thesaurus.owl#C40976"}, {"span": {"begin": 1398, "end": 1401}, "obj": "http://purl.obolibrary.org/obo/OBI_0002110"}, {"span": {"begin": 1398, "end": 1401}, "obj": "http://ncicb.nci.nih.gov/xml/owl/EVS/Thesaurus.owl#C153902"}, {"span": {"begin": 1398, "end": 1401}, "obj": "http://ncicb.nci.nih.gov/xml/owl/EVS/Thesaurus.owl#C71462"}, {"span": {"begin": 1449, "end": 1464}, "obj": "http://ncicb.nci.nih.gov/xml/owl/EVS/Thesaurus.owl#C16199"}]}