{"text": "CAMKII and Calcineurin regulate the lifespan of Caenorhabditis elegans through the FOXO transcription factor DAF-16\nThe insulin-like signaling pathway maintains a relatively short wild-type lifespan in Caenorhabditis elegans by phosphorylating and inactivating DAF-16, the ortholog of the FOXO transcription factors of mammalian cells. DAF-16 is phosphorylated by the AKT kinases, preventing its nuclear translocation. Calcineurin (PP2B phosphatase) also limits the lifespan of C. elegans, but the mechanism through which it does so is unknown. Herein, we show that TAX-6\u2022CNB-1 and UNC-43, the C. elegans Calcineurin and Ca2+/calmodulin-dependent kinase type II (CAMKII) orthologs, respectively, also regulate lifespan through DAF-16. Moreover, UNC-43 regulates DAF-16 in response to various stress conditions, including starvation, heat or oxidative stress, and cooperatively contributes to lifespan regulation by insulin signaling. However, unlike insulin signaling, UNC-43 phosphorylates and activates DAF-16, thus promoting its nuclear localization. The phosphorylation of DAF-16 at S286 by UNC-43 is removed by TAX-6\u2022CNB-1, leading to DAF-16 inactivation. Mammalian FOXO3 is also regulated by CAMKIIA and Calcineurin.\nDOI: http://dx.doi.org/10.7554/eLife.00518.001", "sourcedb": "PMC", "sourceid": "3691573", "divid": 0, "denotations": [{"span": {"begin": 0, "end": 6}, "obj": "http://purl.obolibrary.org/obo/GO_0005954"}, {"span": {"begin": 663, "end": 669}, "obj": "http://purl.obolibrary.org/obo/GO_0005954"}, {"span": {"begin": 0, "end": 6}, "obj": "http://purl.obolibrary.org/obo/PR_000003197"}, {"span": {"begin": 663, "end": 669}, "obj": "http://purl.obolibrary.org/obo/PR_000003197"}, {"span": {"begin": 0, "end": 6}, "obj": "http://purl.obolibrary.org/obo/GO_0004683"}, {"span": {"begin": 663, "end": 669}, "obj": "http://purl.obolibrary.org/obo/GO_0004683"}, {"span": {"begin": 11, "end": 22}, "obj": "http://purl.bioontology.org/ontology/SNOMEDCT/712717007"}, {"span": {"begin": 419, "end": 430}, "obj": "http://purl.bioontology.org/ontology/SNOMEDCT/712717007"}, {"span": {"begin": 605, "end": 616}, "obj": "http://purl.bioontology.org/ontology/SNOMEDCT/712717007"}, {"span": {"begin": 1210, "end": 1221}, "obj": "http://purl.bioontology.org/ontology/SNOMEDCT/712717007"}, {"span": {"begin": 11, "end": 22}, "obj": "http://purl.bioontology.org/ontology/MESH/D019703"}, {"span": {"begin": 419, "end": 430}, "obj": "http://purl.bioontology.org/ontology/MESH/D019703"}, {"span": {"begin": 605, "end": 616}, "obj": "http://purl.bioontology.org/ontology/MESH/D019703"}, {"span": {"begin": 1210, "end": 1221}, "obj": "http://purl.bioontology.org/ontology/MESH/D019703"}, {"span": {"begin": 11, "end": 22}, "obj": "http://ncicb.nci.nih.gov/xml/owl/EVS/Thesaurus.owl#C17275"}, {"span": {"begin": 419, "end": 430}, "obj": "http://ncicb.nci.nih.gov/xml/owl/EVS/Thesaurus.owl#C17275"}, {"span": {"begin": 605, "end": 616}, "obj": "http://ncicb.nci.nih.gov/xml/owl/EVS/Thesaurus.owl#C17275"}, {"span": {"begin": 1210, "end": 1221}, "obj": "http://ncicb.nci.nih.gov/xml/owl/EVS/Thesaurus.owl#C17275"}, {"span": {"begin": 11, "end": 22}, "obj": "http://purl.obolibrary.org/obo/GO_0004722"}, {"span": {"begin": 419, "end": 430}, "obj": "http://purl.obolibrary.org/obo/GO_0004722"}, {"span": {"begin": 605, "end": 616}, "obj": "http://purl.obolibrary.org/obo/GO_0004722"}, {"span": {"begin": 1210, "end": 1221}, "obj": "http://purl.obolibrary.org/obo/GO_0004722"}, {"span": {"begin": 11, "end": 22}, "obj": "http://purl.obolibrary.org/obo/GO_0004723"}, {"span": {"begin": 419, "end": 430}, "obj": "http://purl.obolibrary.org/obo/GO_0004723"}, {"span": {"begin": 605, "end": 616}, "obj": "http://purl.obolibrary.org/obo/GO_0004723"}, {"span": {"begin": 1210, "end": 1221}, "obj": "http://purl.obolibrary.org/obo/GO_0004723"}, {"span": {"begin": 36, "end": 44}, "obj": "http://ncicb.nci.nih.gov/xml/owl/EVS/Thesaurus.owl#C153298"}, {"span": {"begin": 190, "end": 198}, "obj": "http://ncicb.nci.nih.gov/xml/owl/EVS/Thesaurus.owl#C153298"}, {"span": {"begin": 466, "end": 474}, "obj": "http://ncicb.nci.nih.gov/xml/owl/EVS/Thesaurus.owl#C153298"}, {"span": {"begin": 710, "end": 718}, "obj": "http://ncicb.nci.nih.gov/xml/owl/EVS/Thesaurus.owl#C153298"}, {"span": {"begin": 892, "end": 900}, "obj": "http://ncicb.nci.nih.gov/xml/owl/EVS/Thesaurus.owl#C153298"}, {"span": {"begin": 48, "end": 70}, "obj": "http://purl.bioontology.org/ontology/SNOMEDCT/61889003"}, {"span": {"begin": 202, "end": 224}, "obj": "http://purl.bioontology.org/ontology/SNOMEDCT/61889003"}, {"span": {"begin": 48, "end": 70}, "obj": "http://ncicb.nci.nih.gov/xml/owl/EVS/Thesaurus.owl#C14303"}, {"span": {"begin": 202, "end": 224}, "obj": "http://ncicb.nci.nih.gov/xml/owl/EVS/Thesaurus.owl#C14303"}, {"span": {"begin": 478, "end": 488}, "obj": "http://ncicb.nci.nih.gov/xml/owl/EVS/Thesaurus.owl#C14303"}, {"span": {"begin": 594, "end": 604}, "obj": "http://ncicb.nci.nih.gov/xml/owl/EVS/Thesaurus.owl#C14303"}, {"span": {"begin": 48, "end": 70}, "obj": "http://purl.obolibrary.org/obo/NCBITaxon_6239"}, {"span": {"begin": 202, "end": 224}, "obj": "http://purl.obolibrary.org/obo/NCBITaxon_6239"}, {"span": {"begin": 48, "end": 70}, "obj": "http://purl.obolibrary.org/obo/NCBITaxon_6239"}, {"span": {"begin": 202, "end": 224}, "obj": "http://purl.obolibrary.org/obo/NCBITaxon_6239"}, {"span": {"begin": 48, "end": 70}, "obj": "http://purl.bioontology.org/ontology/MESH/D017173"}, {"span": {"begin": 202, "end": 224}, "obj": "http://purl.bioontology.org/ontology/MESH/D017173"}, {"span": {"begin": 48, "end": 62}, "obj": "http://purl.bioontology.org/ontology/MESH/D002107"}, {"span": {"begin": 202, "end": 216}, "obj": "http://purl.bioontology.org/ontology/MESH/D002107"}, {"span": {"begin": 48, "end": 62}, "obj": "http://purl.bioontology.org/ontology/SNOMEDCT/83327008"}, {"span": {"begin": 202, "end": 216}, "obj": "http://purl.bioontology.org/ontology/SNOMEDCT/83327008"}, {"span": {"begin": 83, "end": 87}, "obj": "http://purl.obolibrary.org/obo/PR_O16850"}, {"span": {"begin": 289, "end": 293}, "obj": "http://purl.obolibrary.org/obo/PR_O16850"}, {"span": {"begin": 83, "end": 87}, "obj": "http://ncicb.nci.nih.gov/xml/owl/EVS/Thesaurus.owl#C118892"}, {"span": {"begin": 289, "end": 293}, "obj": "http://ncicb.nci.nih.gov/xml/owl/EVS/Thesaurus.owl#C118892"}, {"span": {"begin": 88, "end": 108}, "obj": "http://purl.bioontology.org/ontology/NDFRT/N0000169818"}, {"span": {"begin": 88, "end": 108}, "obj": "http://purl.bioontology.org/ontology/MESH/D014157"}, {"span": {"begin": 294, "end": 315}, "obj": "http://purl.bioontology.org/ontology/MESH/D014157"}, {"span": {"begin": 88, "end": 108}, "obj": "http://ncicb.nci.nih.gov/xml/owl/EVS/Thesaurus.owl#C17207"}, {"span": {"begin": 88, "end": 108}, "obj": "http://purl.obolibrary.org/obo/GO_0000981"}, {"span": {"begin": 88, "end": 108}, "obj": "http://purl.obolibrary.org/obo/GO_0000982"}, {"span": {"begin": 88, "end": 101}, "obj": "http://ncicb.nci.nih.gov/xml/owl/EVS/Thesaurus.owl#C17208"}, {"span": {"begin": 294, "end": 307}, "obj": "http://ncicb.nci.nih.gov/xml/owl/EVS/Thesaurus.owl#C17208"}, {"span": {"begin": 88, "end": 101}, "obj": "http://purl.obolibrary.org/obo/GO_0006351"}, {"span": {"begin": 294, "end": 307}, "obj": "http://purl.obolibrary.org/obo/GO_0006351"}, {"span": {"begin": 88, "end": 101}, "obj": "http://ncicb.nci.nih.gov/xml/owl/EVS/Thesaurus.owl#C142497"}, {"span": {"begin": 294, "end": 307}, "obj": "http://ncicb.nci.nih.gov/xml/owl/EVS/Thesaurus.owl#C142497"}, {"span": {"begin": 102, "end": 108}, "obj": "http://ncicb.nci.nih.gov/xml/owl/EVS/Thesaurus.owl#C25506"}, {"span": {"begin": 102, "end": 108}, "obj": "http://ncicb.nci.nih.gov/xml/owl/EVS/Thesaurus.owl#C84380"}, {"span": {"begin": 109, "end": 112}, "obj": "http://purl.obolibrary.org/obo/PR_000025662"}, {"span": {"begin": 261, "end": 264}, "obj": "http://purl.obolibrary.org/obo/PR_000025662"}, {"span": {"begin": 336, "end": 339}, "obj": "http://purl.obolibrary.org/obo/PR_000025662"}, {"span": {"begin": 727, "end": 730}, "obj": "http://purl.obolibrary.org/obo/PR_000025662"}, {"span": {"begin": 762, "end": 765}, "obj": "http://purl.obolibrary.org/obo/PR_000025662"}, {"span": {"begin": 1005, "end": 1008}, "obj": "http://purl.obolibrary.org/obo/PR_000025662"}, {"span": {"begin": 1077, "end": 1080}, "obj": "http://purl.obolibrary.org/obo/PR_000025662"}, {"span": {"begin": 1140, "end": 1143}, "obj": "http://purl.obolibrary.org/obo/PR_000025662"}, {"span": {"begin": 109, "end": 112}, "obj": "http://ncicb.nci.nih.gov/xml/owl/EVS/Thesaurus.owl#C95931"}, {"span": {"begin": 261, "end": 264}, "obj": "http://ncicb.nci.nih.gov/xml/owl/EVS/Thesaurus.owl#C95931"}, {"span": {"begin": 336, "end": 339}, "obj": "http://ncicb.nci.nih.gov/xml/owl/EVS/Thesaurus.owl#C95931"}, {"span": {"begin": 727, "end": 730}, "obj": "http://ncicb.nci.nih.gov/xml/owl/EVS/Thesaurus.owl#C95931"}, {"span": {"begin": 762, "end": 765}, "obj": "http://ncicb.nci.nih.gov/xml/owl/EVS/Thesaurus.owl#C95931"}, {"span": {"begin": 1005, "end": 1008}, "obj": "http://ncicb.nci.nih.gov/xml/owl/EVS/Thesaurus.owl#C95931"}, {"span": {"begin": 1077, "end": 1080}, "obj": "http://ncicb.nci.nih.gov/xml/owl/EVS/Thesaurus.owl#C95931"}, {"span": {"begin": 1140, "end": 1143}, "obj": "http://ncicb.nci.nih.gov/xml/owl/EVS/Thesaurus.owl#C95931"}, {"span": {"begin": 109, "end": 112}, "obj": "http://ncicb.nci.nih.gov/xml/owl/EVS/Thesaurus.owl#C95930"}, {"span": {"begin": 261, "end": 264}, "obj": "http://ncicb.nci.nih.gov/xml/owl/EVS/Thesaurus.owl#C95930"}, {"span": {"begin": 336, "end": 339}, "obj": "http://ncicb.nci.nih.gov/xml/owl/EVS/Thesaurus.owl#C95930"}, {"span": {"begin": 727, "end": 730}, "obj": "http://ncicb.nci.nih.gov/xml/owl/EVS/Thesaurus.owl#C95930"}, {"span": {"begin": 762, "end": 765}, "obj": "http://ncicb.nci.nih.gov/xml/owl/EVS/Thesaurus.owl#C95930"}, {"span": {"begin": 1005, "end": 1008}, "obj": "http://ncicb.nci.nih.gov/xml/owl/EVS/Thesaurus.owl#C95930"}, {"span": {"begin": 1077, "end": 1080}, "obj": "http://ncicb.nci.nih.gov/xml/owl/EVS/Thesaurus.owl#C95930"}, {"span": {"begin": 1140, "end": 1143}, "obj": "http://ncicb.nci.nih.gov/xml/owl/EVS/Thesaurus.owl#C95930"}, {"span": {"begin": 109, "end": 112}, "obj": "http://purl.obolibrary.org/obo/PR_Q61475"}, {"span": {"begin": 261, "end": 264}, "obj": "http://purl.obolibrary.org/obo/PR_Q61475"}, {"span": {"begin": 336, "end": 339}, "obj": "http://purl.obolibrary.org/obo/PR_Q61475"}, {"span": {"begin": 727, "end": 730}, "obj": "http://purl.obolibrary.org/obo/PR_Q61475"}, {"span": {"begin": 762, "end": 765}, "obj": "http://purl.obolibrary.org/obo/PR_Q61475"}, {"span": {"begin": 1005, "end": 1008}, "obj": "http://purl.obolibrary.org/obo/PR_Q61475"}, {"span": {"begin": 1077, "end": 1080}, "obj": "http://purl.obolibrary.org/obo/PR_Q61475"}, {"span": {"begin": 1140, "end": 1143}, "obj": "http://purl.obolibrary.org/obo/PR_Q61475"}, {"span": {"begin": 120, "end": 127}, "obj": "http://purl.bioontology.org/ontology/SNOMEDCT/67866001"}, {"span": {"begin": 915, "end": 922}, "obj": "http://purl.bioontology.org/ontology/SNOMEDCT/67866001"}, {"span": {"begin": 950, "end": 957}, "obj": "http://purl.bioontology.org/ontology/SNOMEDCT/67866001"}, {"span": {"begin": 120, "end": 127}, "obj": "http://purl.bioontology.org/ontology/MESH/D007328"}, {"span": {"begin": 915, "end": 922}, "obj": "http://purl.bioontology.org/ontology/MESH/D007328"}, {"span": {"begin": 950, "end": 957}, "obj": "http://purl.bioontology.org/ontology/MESH/D007328"}, {"span": {"begin": 120, "end": 127}, "obj": "http://purl.bioontology.org/ontology/NDFRT/N0000029184"}, {"span": {"begin": 915, "end": 922}, "obj": "http://purl.bioontology.org/ontology/NDFRT/N0000029184"}, {"span": {"begin": 950, "end": 957}, "obj": "http://purl.bioontology.org/ontology/NDFRT/N0000029184"}, {"span": {"begin": 120, "end": 127}, "obj": "http://purl.bioontology.org/ontology/NDFRT/N0000004931"}, {"span": {"begin": 915, "end": 922}, "obj": "http://purl.bioontology.org/ontology/NDFRT/N0000004931"}, {"span": {"begin": 950, "end": 957}, "obj": "http://purl.bioontology.org/ontology/NDFRT/N0000004931"}, {"span": {"begin": 120, "end": 127}, "obj": "http://purl.bioontology.org/ontology/MEDLINEPLUS/C0021641"}, {"span": {"begin": 915, "end": 922}, "obj": "http://purl.bioontology.org/ontology/MEDLINEPLUS/C0021641"}, {"span": {"begin": 950, "end": 957}, "obj": "http://purl.bioontology.org/ontology/MEDLINEPLUS/C0021641"}, {"span": {"begin": 120, "end": 127}, "obj": "http://purl.obolibrary.org/obo/GO_0016088"}, {"span": {"begin": 915, "end": 922}, "obj": "http://purl.obolibrary.org/obo/GO_0016088"}, {"span": {"begin": 950, "end": 957}, "obj": "http://purl.obolibrary.org/obo/GO_0016088"}, {"span": {"begin": 120, "end": 127}, "obj": "http://purl.bioontology.org/ontology/SNOMEDCT/39487003"}, {"span": {"begin": 915, "end": 922}, "obj": "http://purl.bioontology.org/ontology/SNOMEDCT/39487003"}, {"span": {"begin": 950, "end": 957}, "obj": "http://purl.bioontology.org/ontology/SNOMEDCT/39487003"}, {"span": {"begin": 120, "end": 127}, "obj": "http://purl.bioontology.org/ontology/NDFRT/N0000175944"}, {"span": {"begin": 915, "end": 922}, "obj": "http://purl.bioontology.org/ontology/NDFRT/N0000175944"}, {"span": {"begin": 950, "end": 957}, "obj": "http://purl.bioontology.org/ontology/NDFRT/N0000175944"}, {"span": {"begin": 120, "end": 127}, "obj": "http://ncicb.nci.nih.gov/xml/owl/EVS/Thesaurus.owl#C2271"}, {"span": {"begin": 915, "end": 922}, "obj": "http://ncicb.nci.nih.gov/xml/owl/EVS/Thesaurus.owl#C2271"}, {"span": {"begin": 950, "end": 957}, "obj": "http://ncicb.nci.nih.gov/xml/owl/EVS/Thesaurus.owl#C2271"}, {"span": {"begin": 120, "end": 127}, "obj": "http://ncicb.nci.nih.gov/xml/owl/EVS/Thesaurus.owl#C581"}, {"span": {"begin": 915, "end": 922}, "obj": "http://ncicb.nci.nih.gov/xml/owl/EVS/Thesaurus.owl#C581"}, {"span": {"begin": 950, "end": 957}, "obj": "http://ncicb.nci.nih.gov/xml/owl/EVS/Thesaurus.owl#C581"}, {"span": {"begin": 120, "end": 127}, "obj": "http://purl.org/sig/ont/fma/fma83365"}, {"span": {"begin": 915, "end": 922}, "obj": "http://purl.org/sig/ont/fma/fma83365"}, {"span": {"begin": 950, "end": 957}, "obj": "http://purl.org/sig/ont/fma/fma83365"}, {"span": {"begin": 120, "end": 127}, "obj": "http://purl.bioontology.org/ontology/NDFRT/N0000147876"}, {"span": {"begin": 915, "end": 922}, "obj": "http://purl.bioontology.org/ontology/NDFRT/N0000147876"}, {"span": {"begin": 950, "end": 957}, "obj": "http://purl.bioontology.org/ontology/NDFRT/N0000147876"}, {"span": {"begin": 120, "end": 127}, "obj": "http://purl.bioontology.org/ontology/OMIM/176730"}, {"span": {"begin": 915, "end": 922}, "obj": "http://purl.bioontology.org/ontology/OMIM/176730"}, {"span": {"begin": 950, "end": 957}, "obj": "http://purl.bioontology.org/ontology/OMIM/176730"}, {"span": {"begin": 120, "end": 127}, "obj": "http://purl.bioontology.org/ontology/MEDDRA/10022468"}, {"span": {"begin": 915, "end": 922}, "obj": "http://purl.bioontology.org/ontology/MEDDRA/10022468"}, {"span": {"begin": 950, "end": 957}, "obj": "http://purl.bioontology.org/ontology/MEDDRA/10022468"}, {"span": {"begin": 120, "end": 127}, "obj": "http://ncicb.nci.nih.gov/xml/owl/EVS/Thesaurus.owl#C74788"}, {"span": {"begin": 915, "end": 922}, "obj": "http://ncicb.nci.nih.gov/xml/owl/EVS/Thesaurus.owl#C74788"}, {"span": {"begin": 950, "end": 957}, "obj": "http://ncicb.nci.nih.gov/xml/owl/EVS/Thesaurus.owl#C74788"}, {"span": {"begin": 120, "end": 127}, "obj": "http://purl.obolibrary.org/obo/PR_000009054"}, {"span": {"begin": 915, "end": 922}, "obj": "http://purl.obolibrary.org/obo/PR_000009054"}, {"span": {"begin": 950, "end": 957}, "obj": "http://purl.obolibrary.org/obo/PR_000009054"}, {"span": {"begin": 133, "end": 150}, "obj": "http://purl.obolibrary.org/obo/PW_0000003"}, {"span": {"begin": 133, "end": 150}, "obj": "http://purl.obolibrary.org/obo/GO_0007165"}, {"span": {"begin": 133, "end": 150}, "obj": "http://ncicb.nci.nih.gov/xml/owl/EVS/Thesaurus.owl#C17132"}, {"span": {"begin": 133, "end": 142}, "obj": "http://purl.obolibrary.org/obo/GO_0023052"}, {"span": {"begin": 923, "end": 932}, "obj": "http://purl.obolibrary.org/obo/GO_0023052"}, {"span": {"begin": 958, "end": 967}, "obj": "http://purl.obolibrary.org/obo/GO_0023052"}, {"span": {"begin": 133, "end": 142}, "obj": "http://ncicb.nci.nih.gov/xml/owl/EVS/Thesaurus.owl#C17133"}, {"span": {"begin": 923, "end": 932}, "obj": "http://ncicb.nci.nih.gov/xml/owl/EVS/Thesaurus.owl#C17133"}, {"span": {"begin": 958, "end": 967}, "obj": "http://ncicb.nci.nih.gov/xml/owl/EVS/Thesaurus.owl#C17133"}, {"span": {"begin": 143, "end": 150}, "obj": "http://ncicb.nci.nih.gov/xml/owl/EVS/Thesaurus.owl#C20633"}, {"span": {"begin": 143, "end": 150}, "obj": "http://ncicb.nci.nih.gov/xml/owl/EVS/Thesaurus.owl#C54214"}, {"span": {"begin": 143, "end": 150}, "obj": "http://purl.obolibrary.org/obo/PW_0000001"}, {"span": {"begin": 174, "end": 179}, "obj": "http://ncicb.nci.nih.gov/xml/owl/EVS/Thesaurus.owl#C73939"}, {"span": {"begin": 174, "end": 179}, "obj": "http://ncicb.nci.nih.gov/xml/owl/EVS/Thesaurus.owl#C25249"}, {"span": {"begin": 174, "end": 179}, "obj": "http://purl.bioontology.org/ontology/OMIM/MTHU003639"}, {"span": {"begin": 174, "end": 179}, "obj": "http://purl.bioontology.org/ontology/SNOMEDCT/367450005"}, {"span": {"begin": 180, "end": 184}, "obj": "http://purl.bioontology.org/ontology/SNOMEDCT/262290003"}, {"span": {"begin": 185, "end": 189}, "obj": "http://purl.bioontology.org/ontology/SNOMEDCT/410656007"}, {"span": {"begin": 654, "end": 658}, "obj": "http://purl.bioontology.org/ontology/SNOMEDCT/410656007"}, {"span": {"begin": 185, "end": 189}, "obj": "http://ncicb.nci.nih.gov/xml/owl/EVS/Thesaurus.owl#C25284"}, {"span": {"begin": 654, "end": 658}, "obj": "http://ncicb.nci.nih.gov/xml/owl/EVS/Thesaurus.owl#C25284"}, {"span": {"begin": 273, "end": 281}, "obj": "http://ncicb.nci.nih.gov/xml/owl/EVS/Thesaurus.owl#C28708"}, {"span": {"begin": 319, "end": 328}, "obj": "http://ncicb.nci.nih.gov/xml/owl/EVS/Thesaurus.owl#C14234"}, {"span": {"begin": 1161, "end": 1170}, "obj": "http://ncicb.nci.nih.gov/xml/owl/EVS/Thesaurus.owl#C14234"}, {"span": {"begin": 329, "end": 334}, "obj": "http://ncicb.nci.nih.gov/xml/owl/EVS/Thesaurus.owl#C48938"}, {"span": {"begin": 329, "end": 334}, "obj": "http://purl.bioontology.org/ontology/NDFRT/N0000184307"}, {"span": {"begin": 329, "end": 334}, "obj": "http://ncicb.nci.nih.gov/xml/owl/EVS/Thesaurus.owl#C12508"}, {"span": {"begin": 329, "end": 334}, "obj": "http://purl.bioontology.org/ontology/MESH/D002477"}, {"span": {"begin": 368, "end": 371}, "obj": "http://purl.obolibrary.org/obo/PR_P31750"}, {"span": {"begin": 368, "end": 371}, "obj": "http://ncicb.nci.nih.gov/xml/owl/EVS/Thesaurus.owl#C41625"}, {"span": {"begin": 368, "end": 371}, "obj": "http://purl.obolibrary.org/obo/PR_000002190"}, {"span": {"begin": 368, "end": 371}, "obj": "http://purl.obolibrary.org/obo/PR_P54644"}, {"span": {"begin": 368, "end": 371}, "obj": "http://purl.obolibrary.org/obo/PR_000029189"}, {"span": {"begin": 368, "end": 371}, "obj": "http://purl.obolibrary.org/obo/PR_Q8INB9"}, {"span": {"begin": 396, "end": 417}, "obj": "http://ncicb.nci.nih.gov/xml/owl/EVS/Thesaurus.owl#C28506"}, {"span": {"begin": 396, "end": 403}, "obj": "http://ncicb.nci.nih.gov/xml/owl/EVS/Thesaurus.owl#C13361"}, {"span": {"begin": 1032, "end": 1039}, "obj": "http://ncicb.nci.nih.gov/xml/owl/EVS/Thesaurus.owl#C13361"}, {"span": {"begin": 404, "end": 417}, "obj": "http://ncicb.nci.nih.gov/xml/owl/EVS/Thesaurus.owl#C89777"}, {"span": {"begin": 404, "end": 417}, "obj": "http://ncicb.nci.nih.gov/xml/owl/EVS/Thesaurus.owl#C25756"}, {"span": {"begin": 437, "end": 448}, "obj": "http://purl.obolibrary.org/obo/GO_0016791"}, {"span": {"begin": 437, "end": 448}, "obj": "http://purl.bioontology.org/ontology/SNOMEDCT/130132002"}, {"span": {"begin": 437, "end": 448}, "obj": "http://ncicb.nci.nih.gov/xml/owl/EVS/Thesaurus.owl#C16981"}, {"span": {"begin": 437, "end": 448}, "obj": "http://purl.bioontology.org/ontology/SNOMEDCT/736208004"}, {"span": {"begin": 498, "end": 507}, "obj": "http://ncicb.nci.nih.gov/xml/owl/EVS/Thesaurus.owl#C50285"}, {"span": {"begin": 498, "end": 507}, "obj": "http://ncicb.nci.nih.gov/xml/owl/EVS/Thesaurus.owl#C25343"}, {"span": {"begin": 498, "end": 507}, "obj": "http://purl.bioontology.org/ontology/SNOMEDCT/278109006"}, {"span": {"begin": 536, "end": 543}, "obj": "http://purl.bioontology.org/ontology/SNOMEDCT/261665006"}, {"span": {"begin": 536, "end": 543}, "obj": "http://ncicb.nci.nih.gov/xml/owl/EVS/Thesaurus.owl#C38311"}, {"span": {"begin": 536, "end": 543}, "obj": "http://ncicb.nci.nih.gov/xml/owl/EVS/Thesaurus.owl#C150001"}, {"span": {"begin": 536, "end": 543}, "obj": "http://ncicb.nci.nih.gov/xml/owl/EVS/Thesaurus.owl#C150002"}, {"span": {"begin": 536, "end": 543}, "obj": "http://ncicb.nci.nih.gov/xml/owl/EVS/Thesaurus.owl#C150003"}, {"span": {"begin": 536, "end": 543}, "obj": "http://ncicb.nci.nih.gov/xml/owl/EVS/Thesaurus.owl#C123772"}, {"span": {"begin": 536, "end": 543}, "obj": "http://ncicb.nci.nih.gov/xml/owl/EVS/Thesaurus.owl#C17998"}, {"span": {"begin": 566, "end": 569}, "obj": "http://purl.obolibrary.org/obo/PR_Q61330"}, {"span": {"begin": 1116, "end": 1119}, "obj": "http://purl.obolibrary.org/obo/PR_Q61330"}, {"span": {"begin": 566, "end": 569}, "obj": "http://purl.obolibrary.org/obo/PR_000005667"}, {"span": {"begin": 1116, "end": 1119}, "obj": "http://purl.obolibrary.org/obo/PR_000005667"}, {"span": {"begin": 566, "end": 569}, "obj": "http://ncicb.nci.nih.gov/xml/owl/EVS/Thesaurus.owl#C54075"}, {"span": {"begin": 1116, "end": 1119}, "obj": "http://ncicb.nci.nih.gov/xml/owl/EVS/Thesaurus.owl#C54075"}, {"span": {"begin": 582, "end": 585}, "obj": "http://ncicb.nci.nih.gov/xml/owl/EVS/Thesaurus.owl#C150902"}, {"span": {"begin": 745, "end": 748}, "obj": "http://ncicb.nci.nih.gov/xml/owl/EVS/Thesaurus.owl#C150902"}, {"span": {"begin": 969, "end": 972}, "obj": "http://ncicb.nci.nih.gov/xml/owl/EVS/Thesaurus.owl#C150902"}, {"span": {"begin": 1095, "end": 1098}, "obj": "http://ncicb.nci.nih.gov/xml/owl/EVS/Thesaurus.owl#C150902"}, {"span": {"begin": 621, "end": 625}, "obj": "http://ncicb.nci.nih.gov/xml/owl/EVS/Thesaurus.owl#C68242"}, {"span": {"begin": 621, "end": 625}, "obj": "http://ncicb.nci.nih.gov/xml/owl/EVS/Thesaurus.owl#C61660"}, {"span": {"begin": 621, "end": 624}, "obj": "http://ncicb.nci.nih.gov/xml/owl/EVS/Thesaurus.owl#C54637"}, {"span": {"begin": 621, "end": 624}, "obj": "http://purl.obolibrary.org/obo/PR_000004918"}, {"span": {"begin": 621, "end": 624}, "obj": "http://ncicb.nci.nih.gov/xml/owl/EVS/Thesaurus.owl#C1789"}, {"span": {"begin": 621, "end": 624}, "obj": "http://purl.obolibrary.org/obo/PR_P42737"}, {"span": {"begin": 626, "end": 636}, "obj": "http://ncicb.nci.nih.gov/xml/owl/EVS/Thesaurus.owl#C16375"}, {"span": {"begin": 626, "end": 636}, "obj": "http://purl.obolibrary.org/obo/PR_000004978"}, {"span": {"begin": 626, "end": 636}, "obj": "http://purl.org/sig/ont/fma/fma62343"}, {"span": {"begin": 626, "end": 636}, "obj": "http://purl.bioontology.org/ontology/SNOMEDCT/41649004"}, {"span": {"begin": 626, "end": 636}, "obj": "http://purl.bioontology.org/ontology/MESH/D002147"}, {"span": {"begin": 637, "end": 646}, "obj": "http://ncicb.nci.nih.gov/xml/owl/EVS/Thesaurus.owl#C63905"}, {"span": {"begin": 637, "end": 646}, "obj": "http://ncicb.nci.nih.gov/xml/owl/EVS/Thesaurus.owl#C78344"}, {"span": {"begin": 637, "end": 646}, "obj": "http://ncicb.nci.nih.gov/xml/owl/EVS/Thesaurus.owl#C131934"}, {"span": {"begin": 637, "end": 646}, "obj": "http://ncicb.nci.nih.gov/xml/owl/EVS/Thesaurus.owl#C131954"}, {"span": {"begin": 637, "end": 646}, "obj": "http://purl.bioontology.org/ontology/SNOMEDCT/371154000"}, {"span": {"begin": 637, "end": 646}, "obj": "http://ncicb.nci.nih.gov/xml/owl/EVS/Thesaurus.owl#C131948"}, {"span": {"begin": 647, "end": 653}, "obj": "http://purl.bioontology.org/ontology/SNOMEDCT/736215007"}, {"span": {"begin": 647, "end": 653}, "obj": "http://purl.bioontology.org/ontology/SNOMEDCT/304257007"}, {"span": {"begin": 647, "end": 653}, "obj": "http://purl.bioontology.org/ontology/NDFRT/N0000168200"}, {"span": {"begin": 647, "end": 653}, "obj": "http://ncicb.nci.nih.gov/xml/owl/EVS/Thesaurus.owl#C28597"}, {"span": {"begin": 647, "end": 653}, "obj": "http://purl.bioontology.org/ontology/MESH/D010770"}, {"span": {"begin": 772, "end": 780}, "obj": "http://ncicb.nci.nih.gov/xml/owl/EVS/Thesaurus.owl#C25755"}, {"span": {"begin": 772, "end": 780}, "obj": "http://ncicb.nci.nih.gov/xml/owl/EVS/Thesaurus.owl#C50995"}, {"span": {"begin": 772, "end": 780}, "obj": "http://ncicb.nci.nih.gov/xml/owl/EVS/Thesaurus.owl#C49149"}, {"span": {"begin": 772, "end": 780}, "obj": "http://ncicb.nci.nih.gov/xml/owl/EVS/Thesaurus.owl#C82658"}, {"span": {"begin": 792, "end": 798}, "obj": "http://purl.bioontology.org/ontology/MEDLINEPLUS/C0038435"}, {"span": {"begin": 851, "end": 857}, "obj": "http://purl.bioontology.org/ontology/MEDLINEPLUS/C0038435"}, {"span": {"begin": 792, "end": 798}, "obj": "http://purl.bioontology.org/ontology/MEDDRA/10042209"}, {"span": {"begin": 851, "end": 857}, "obj": "http://purl.bioontology.org/ontology/MEDDRA/10042209"}, {"span": {"begin": 792, "end": 798}, "obj": "http://purl.bioontology.org/ontology/SNOMEDCT/73595000"}, {"span": {"begin": 851, "end": 857}, "obj": "http://purl.bioontology.org/ontology/SNOMEDCT/73595000"}, {"span": {"begin": 792, "end": 798}, "obj": "http://purl.bioontology.org/ontology/SNOMEDCT/262188008"}, {"span": {"begin": 851, "end": 857}, "obj": "http://purl.bioontology.org/ontology/SNOMEDCT/262188008"}, {"span": {"begin": 792, "end": 798}, "obj": "http://ncicb.nci.nih.gov/xml/owl/EVS/Thesaurus.owl#C35041"}, {"span": {"begin": 851, "end": 857}, "obj": "http://ncicb.nci.nih.gov/xml/owl/EVS/Thesaurus.owl#C35041"}, {"span": {"begin": 811, "end": 820}, "obj": "http://purl.bioontology.org/ontology/SNOMEDCT/55919000"}, {"span": {"begin": 821, "end": 831}, "obj": "http://purl.bioontology.org/ontology/MESH/D013217"}, {"span": {"begin": 821, "end": 831}, "obj": "http://purl.bioontology.org/ontology/NDFRT/N0000002820"}, {"span": {"begin": 821, "end": 831}, "obj": "http://purl.bioontology.org/ontology/MEDDRA/10041954"}, {"span": {"begin": 821, "end": 831}, "obj": "http://purl.bioontology.org/ontology/SNOMEDCT/212968006"}, {"span": {"begin": 833, "end": 837}, "obj": "http://purl.bioontology.org/ontology/MESH/D006358"}, {"span": {"begin": 833, "end": 837}, "obj": "http://purl.bioontology.org/ontology/SNOMEDCT/88999006"}, {"span": {"begin": 833, "end": 837}, "obj": "http://www.owl-ontologies.com/Ontology1184060740.owl#Class_50"}, {"span": {"begin": 841, "end": 857}, "obj": "http://purl.bioontology.org/ontology/MESH/D018384"}, {"span": {"begin": 841, "end": 857}, "obj": "http://ncicb.nci.nih.gov/xml/owl/EVS/Thesaurus.owl#C17741"}, {"span": {"begin": 901, "end": 911}, "obj": "http://ncicb.nci.nih.gov/xml/owl/EVS/Thesaurus.owl#C48805"}, {"span": {"begin": 901, "end": 911}, "obj": "http://purl.obolibrary.org/obo/GO_0065007"}, {"span": {"begin": 901, "end": 911}, "obj": "http://ncicb.nci.nih.gov/xml/owl/EVS/Thesaurus.owl#C68821"}, {"span": {"begin": 1185, "end": 1194}, "obj": "http://ncicb.nci.nih.gov/xml/owl/EVS/Thesaurus.owl#C68821"}, {"span": {"begin": 1018, "end": 1027}, "obj": "http://ncicb.nci.nih.gov/xml/owl/EVS/Thesaurus.owl#C61391"}, {"span": {"begin": 1040, "end": 1052}, "obj": "http://purl.obolibrary.org/obo/GO_0051179"}, {"span": {"begin": 1040, "end": 1052}, "obj": "http://ncicb.nci.nih.gov/xml/owl/EVS/Thesaurus.owl#C28264"}, {"span": {"begin": 1058, "end": 1073}, "obj": "http://purl.bioontology.org/ontology/SNOMEDCT/363262008"}, {"span": {"begin": 1058, "end": 1073}, "obj": "http://purl.bioontology.org/ontology/MESH/D010766"}, {"span": {"begin": 1058, "end": 1073}, "obj": "http://ncicb.nci.nih.gov/xml/owl/EVS/Thesaurus.owl#C16983"}, {"span": {"begin": 1058, "end": 1073}, "obj": "http://purl.obolibrary.org/obo/GO_0016310"}, {"span": {"begin": 1058, "end": 1073}, "obj": "http://ncicb.nci.nih.gov/xml/owl/EVS/Thesaurus.owl#C18496"}, {"span": {"begin": 1105, "end": 1112}, "obj": "http://ncicb.nci.nih.gov/xml/owl/EVS/Thesaurus.owl#C25650"}, {"span": {"begin": 1129, "end": 1136}, "obj": "http://ncicb.nci.nih.gov/xml/owl/EVS/Thesaurus.owl#C25629"}, {"span": {"begin": 1171, "end": 1176}, "obj": "http://purl.obolibrary.org/obo/PR_000007641"}, {"span": {"begin": 1171, "end": 1176}, "obj": "http://ncicb.nci.nih.gov/xml/owl/EVS/Thesaurus.owl#C52907"}, {"span": {"begin": 1171, "end": 1176}, "obj": "http://ncicb.nci.nih.gov/xml/owl/EVS/Thesaurus.owl#C28519"}, {"span": {"begin": 1223, "end": 1226}, "obj": "http://purl.obolibrary.org/obo/OBI_0002110"}, {"span": {"begin": 1238, "end": 1241}, "obj": "http://purl.obolibrary.org/obo/OBI_0002110"}, {"span": {"begin": 1223, "end": 1226}, "obj": "http://ncicb.nci.nih.gov/xml/owl/EVS/Thesaurus.owl#C153902"}, {"span": {"begin": 1238, "end": 1241}, "obj": "http://ncicb.nci.nih.gov/xml/owl/EVS/Thesaurus.owl#C153902"}, {"span": {"begin": 1223, "end": 1226}, "obj": "http://ncicb.nci.nih.gov/xml/owl/EVS/Thesaurus.owl#C71462"}, {"span": {"begin": 1238, "end": 1241}, "obj": "http://ncicb.nci.nih.gov/xml/owl/EVS/Thesaurus.owl#C71462"}, {"span": {"begin": 1228, "end": 1232}, "obj": "http://ncicb.nci.nih.gov/xml/owl/EVS/Thesaurus.owl#C142279"}, {"span": {"begin": 1242, "end": 1245}, "obj": "http://ncicb.nci.nih.gov/xml/owl/EVS/Thesaurus.owl#C19711"}, {"span": {"begin": 1242, "end": 1245}, "obj": "http://ncicb.nci.nih.gov/xml/owl/EVS/Thesaurus.owl#C19223"}]}